{
  "streams": [
    {
      "id": "e70f",
      "title": "this is my stream",
      "description": "physics is it"
    },
    {
      "id": "43d3",
      "title": "this is my stream",
      "description": "physics is it"
    },
    {
      "id": "734e",
      "title": "this is my stream",
      "description": "physics is it"
    },
    {
      "id": "8507",
      "title": "this is my stream",
      "description": "physics is it"
    },
    {
      "id": "6909",
      "title": "hello",
      "description": "Hi"
    },
    {
      "id": "71d6",
      "title": "hello",
      "description": "Hi"
    },
    {
      "id": "10bf",
      "title": "Hi",
      "description": "Hello"
    }
  ]
}